DictAllPaths
